vajirayana/__init__.py
vajirayana/scraper.py
vajirayana-0.0.2.dist-info/LICENSE.md
vajirayana-0.0.2.dist-info/METADATA
vajirayana-0.0.2.dist-info/WHEEL
vajirayana-0.0.2.dist-info/top_level.txt
vajirayana-0.0.2.dist-info/RECORD
